datafunc/__init__.py
datafunc-0.0.4.dist-info/LICENSE.md
datafunc-0.0.4.dist-info/WHEEL
datafunc-0.0.4.dist-info/METADATA
datafunc-0.0.4.dist-info/RECORD
