Metadata-Version: 2.1
Name: datafunc
Version: 0.0.4
Summary: Python functions for various dict, list, and other data structures.
Home-page: https://github.com/tensortom/datafunc
License: MIT
Keywords: python,python3,data,dict,utilities,util,tools,dict,dictionary,data,mo-dots,list,dotty_dict,iterate,iterator
Author: Tom A.
Author-email: 14287229+TensorTom@users.noreply.github.com
Requires-Python: >=3.6,<4.0
Classifier: License :: OSI Approved :: MIT License
Classifier: Programming Language :: Python :: 3
Classifier: Programming Language :: Python :: 3.6
Classifier: Programming Language :: Python :: 3.7
Classifier: Programming Language :: Python :: 3.8
Classifier: Programming Language :: Python :: 3.9
Requires-Dist: dotty-dict
Requires-Dist: mo-dots
Requires-Dist: traversy (>=0.1.2)
Project-URL: Repository, https://github.com/tensortom/datafunc
